dhuolib/__init__.py
dhuolib/config.py
dhuolib/messages.py
dhuolib/repository.py
dhuolib/services.py
dhuolib/utils.py
dhuolib/validations.py
dhuolib/clients/__init__.py
dhuolib/clients/experiment.py
dhuolib/clients/platform.py
dhuolib-0.2.3.dist-info/METADATA
dhuolib-0.2.3.dist-info/WHEEL
dhuolib-0.2.3.dist-info/top_level.txt
dhuolib-0.2.3.dist-info/RECORD
