Metadata-Version: 2.1
Name: dhuolib
Version: 0.2.3
Summary: UNKNOWN
Home-page: https://gitlab.engdb.com.br/dhuo-plat/dhuo-data/data-science/dhuolib
Author: DHuO Data Team
Author-email: diego.salles@engdb.com.br
License: UNKNOWN
Platform: any
Requires-Dist: oci==2.125.3
Requires-Dist: SQLAlchemy==2.0.30
Requires-Dist: oracledb==2.2.0
Requires-Dist: pydantic==2.7.3
Requires-Dist: Werkzeug==3.0.3
Requires-Dist: requests==2.26.0
Requires-Dist: pandas==2.1.2
Provides-Extra: interactive
Requires-Dist: mypy==1.5.1; extra == "interactive"
Requires-Dist: flake8==6.1.0; extra == "interactive"
Requires-Dist: black==22.3.0; extra == "interactive"
Requires-Dist: pytest-cov~=4.0; extra == "interactive"
Requires-Dist: pytest~=7.0; extra == "interactive"
Requires-Dist: twine==3.4.2; extra == "interactive"
Requires-Dist: pydantic==2.7.3; extra == "interactive"
Requires-Dist: Werkzeug==3.0.3; extra == "interactive"
Requires-Dist: oci==2.125.3; extra == "interactive"
Requires-Dist: SQLAlchemy==2.0.30; extra == "interactive"
Requires-Dist: oracledb==2.2.0; extra == "interactive"
Requires-Dist: requests==2.26.0; extra == "interactive"
Requires-Dist: pandas==2.1.2; extra == "interactive"
